staphscope/__init__.py
staphscope/cli.py
staphscope/core.py
staphscope_typing_tool-0.1.0.dist-info/licenses/LICENSE
tests/__init__.py
tests/test_staphscope.py
staphscope_typing_tool-0.1.0.dist-info/METADATA
staphscope_typing_tool-0.1.0.dist-info/WHEEL
staphscope_typing_tool-0.1.0.dist-info/entry_points.txt
staphscope_typing_tool-0.1.0.dist-info/top_level.txt
staphscope_typing_tool-0.1.0.dist-info/RECORD
