Metadata-Version: 2.4
Name: staphscope-typing-tool
Version: 0.1.0
Summary: Staphscope Typing Tool — MLST + spa + SCCmec typing for Staphylococcus aureus
Home-page: https://github.com/bbeckley-hub/staphscope-typing-tool
Author: Beckley Brown
Author-email: brownbeckley94@gmail.com
Project-URL: Bug Reports, https://github.com/bbeckley-hub/staphscope-typing-tool/issues
Project-URL: Source, https://github.com/bbeckley-hub/staphscope-typing-tool
Keywords: bioinformatics,microbiology,staphylococcus,typing,mlst,spa,sccmec
Classifier: Development Status :: 4 - Beta
Classifier: Intended Audience :: Science/Research
Classifier: Topic :: Scientific/Engineering :: Bio-Informatics
Classifier: License :: OSI Approved :: MIT License
Classifier: Programming Language :: Python :: 3
Classifier: Programming Language :: Python :: 3.6
Classifier: Programming Language :: Python :: 3.7
Classifier: Programming Language :: Python :: 3.8
Classifier: Programming Language :: Python :: 3.9
Classifier: Programming Language :: Python :: 3.10
Classifier: Programming Language :: Python :: 3 :: Only
Requires-Python: >=3.6, <4
License-File: LICENSE
Requires-Dist: biopython>=1.79
Requires-Dist: pandas>=1.3.0
Dynamic: author
Dynamic: author-email
Dynamic: classifier
Dynamic: description
Dynamic: description-content-type
Dynamic: home-page
Dynamic: keywords
Dynamic: license-file
Dynamic: project-url
Dynamic: requires-dist
Dynamic: requires-python
Dynamic: summary
